{
  "doc_id": "32-264-0018",
  "title": {
    "zh_CN": "台南极乐寺会客谈话—所有一切错误都是太冲动",
    "zh_TW": "台南極樂寺會客談話—所有一切錯誤都是太衝動"
  },
  "authors": [],
  "volume": {
    "zh_CN": "第十八集",
    "zh_TW": "第十八集"
  },
  "year": "2020",
  "location": {
    "zh_CN": "台湾台南极乐寺",
    "zh_TW": "台灣台南極樂寺"
  },
  "doc_number": "32-264-0018",
  "total_paragraphs": 4,
  "paragraphs": [
    {
      "id": "32-264-0018_p0001",
      "zh_CN": "起心动念很奥妙。我们的老祖宗、诸佛菩萨都是教我们不要起心、不要动念，高明。所以你无论在什么地方，控制住，境界现前，我只要不起心不动念，看得清楚，摸得着，看得到，你就能够走到最好的这一阶段。所有一切错误都是太冲动，真正能做到很冷静，不为外境所动摇，很少有错误。自己永远站在客观的立场上，世界假的，不是真的，何必这么认真？",
      "zh_TW": "起心動念很奧妙。我們的老祖宗、諸佛菩薩都是教我們不要起心、不要動念，高明。所以你無論在什麼地方，控制住，境界現前，我只要不起心不動念，看得清楚，摸得著，看得到，你就能夠走到最好的這一階段。所有一切錯誤都是太衝動，真正能做到很冷靜，不為外境所動搖，很少有錯誤。自己永遠站在客觀的立場上，世界假的，不是真的，何必這麼認真？"
    },
    {
      "id": "32-264-0018_p0002",
      "zh_CN": "我什么都不要，摆在我面前，我第一个思考的怎么分配给大家，都分配给大家就没事了。大家都有责任，参与的都有，无论金银财宝、物质精神，大家都有分。不要有占有的念头，就没有痛苦；你有占有，你念念想挖一块，那个很苦。",
      "zh_TW": "我什麼都不要，擺在我面前，我第一個思考的怎麼分配給大家，都分配給大家就沒事了。大家都有責任，參與的都有，無論金銀財寶、物質精神，大家都有分。不要有佔有的念頭，就沒有痛苦；你有佔有，你念念想挖一塊，那個很苦。"
    },
    {
      "id": "32-264-0018_p0003",
      "zh_CN": "有人问我：「你怕不怕死？」我说我不怕死。怕死的人有得失，我没有得失，得失我不要。没有得失就没有操心的地方，没有想占有的地方，很自在。我不跟人争，你要全拿去。为什么？你有得失，我没有得失，我应该让给你。为什么？我没有痛苦，你有痛苦。",
      "zh_TW": "有人問我：「你怕不怕死？」我說我不怕死。怕死的人有得失，我沒有得失，得失我不要。沒有得失就沒有操心的地方，沒有想佔有的地方，很自在。我不跟人爭，你要全拿去。為什麼？你有得失，我沒有得失，我應該讓給你。為什麼？我沒有痛苦，你有痛苦。"
    },
    {
      "id": "32-264-0018_p0004",
      "zh_CN": "老和尚有一个口头禅：一切来了，随它去吧！要不要占有？有我一分，他应该要分给我；他要不分给我，那口也很难吃下去。佛家知道，该是你的还是你的，不该是你的你拿不去，很有意思。",
      "zh_TW": "老和尚有一個口頭禪：一切來了，隨它去吧！要不要佔有？有我一分，他應該要分給我；他要不分給我，那口也很難吃下去。佛家知道，該是你的還是你的，不該是你的你拿不去，很有意思。"
    }
  ]
}